simple_item_plugin/__init__.py
simple_item_plugin/assets/guide/font/big.json
simple_item_plugin/assets/guide/font/medium.json
simple_item_plugin/assets/guide/furnace_craft.png
simple_item_plugin/assets/guide/logo/github.png
simple_item_plugin/assets/guide/logo/modrinth.png
simple_item_plugin/assets/guide/logo/pmc.png
simple_item_plugin/assets/guide/logo/smithed.png
simple_item_plugin/assets/guide/none_2.png
simple_item_plugin/assets/guide/none_2_release.png
simple_item_plugin/assets/guide/none_3.png
simple_item_plugin/assets/guide/none_3_release.png
simple_item_plugin/assets/guide/none_4.png
simple_item_plugin/assets/guide/none_4_release.png
simple_item_plugin/assets/guide/none_5.png
simple_item_plugin/assets/guide/none_5_release.png
simple_item_plugin/assets/guide/template_craft.png
simple_item_plugin/assets/guide/template_result.png
simple_item_plugin/assets/minecraft_font.ttf
simple_item_plugin/crafting.py
simple_item_plugin/guide.py
simple_item_plugin/item.py
simple_item_plugin/mineral.py
simple_item_plugin/plugin.py
simple_item_plugin/types.py
simple_item_plugin/utils.py
simple_item_plugin/versioning/README.md
simple_item_plugin/versioning/__init__.py
simple_item_plugin/versioning/api.py
simple_item_plugin/versioning/load.py
simple_item_plugin/versioning/models.py
simple_item_plugin/versioning/plugin.py
simple_item_plugin/versioning/types.py
simple_item_plugin/versioning/utils.py
simple_item_plugin-0.28.0.dist-info/LICENSE
simple_item_plugin-0.28.0.dist-info/METADATA
simple_item_plugin-0.28.0.dist-info/WHEEL
simple_item_plugin-0.28.0.dist-info/RECORD
