Metadata-Version: 2.1
Name: simple-item-plugin
Version: 0.28.0
Summary: 
License: MIT
Author: edayot
Author-email: pro.e.dayot@gmail.com
Requires-Python: >=3.12,<4.0
Classifier: License :: OSI Approved :: MIT License
Classifier: Programming Language :: Python :: 3
Classifier: Programming Language :: Python :: 3.12
Requires-Dist: beet (>=0.108.3)
Requires-Dist: bolt (>=0.48.0)
Requires-Dist: mecha (>=0.95.2)
Requires-Dist: model-resolver (>=1.1.0)
Requires-Dist: weld-deps (>=0.8.0)
